GeneratorFEC/__init__.py
GeneratorFEC/generator.py
GeneratorFEC-0.0.1.dist-info/LICENSE
GeneratorFEC-0.0.1.dist-info/METADATA
GeneratorFEC-0.0.1.dist-info/WHEEL
GeneratorFEC-0.0.1.dist-info/top_level.txt
GeneratorFEC-0.0.1.dist-info/RECORD
